atilo/__init__.py
atilo/atilo.py
atilo-0.4.3.dist-info/LICENSE
atilo-0.4.3.dist-info/METADATA
atilo-0.4.3.dist-info/WHEEL
atilo-0.4.3.dist-info/entry_points.txt
atilo-0.4.3.dist-info/top_level.txt
atilo-0.4.3.dist-info/RECORD
