Metadata-Version: 2.1
Name: atilo
Version: 0.4.3
Summary: Install linux on termux.
Home-page: https://github.com/WqyJh/python-atilo
Author: wqy
Author-email: qiyingwangwqy@gmail.com
License: UNKNOWN
Keywords: termux,linux,android
Platform: UNKNOWN
Classifier: Operating System :: Android
Classifier: Operating System :: POSIX :: Linux
Classifier: Programming Language :: Python :: 3 :: Only
Requires-Dist: plumbum
